__init__.py
_version.py
constants.py
fitterpp.py
function_wrapper.py
latin_cube.py
logs.py
util.py
fitterpp-0.0.8.dist-info/LICENSE
fitterpp-0.0.8.dist-info/METADATA
fitterpp-0.0.8.dist-info/WHEEL
fitterpp-0.0.8.dist-info/top_level.txt
fitterpp-0.0.8.dist-info/RECORD
