Metadata-Version: 2.1
Name: fitterpp
Version: 0.0.8
Summary: Fitter parameters for an SBML model
Author-email: Joseph Hellerstein <joseph.hellerstein@gmail.com>
License: MIT License
Project-URL: Homepage, https://github.com/ModelEngineering/fitterpp
Requires-Python: >=3.6
License-File: LICENSE
Requires-Dist: jupyterlab
Requires-Dist: lhsmdu
Requires-Dist: lmfit
Requires-Dist: matplotlib
Requires-Dist: nose
Requires-Dist: numpy
Requires-Dist: pandas
